HISTORY.rst
LICENSE
MANIFEST.in
README.rst
setup.cfg
setup.py
eqsig/__about__.py
eqsig/__init__.py
eqsig/design_spectra.py
eqsig/displacements.py
eqsig/duhamels.py
eqsig/exceptions.py
eqsig/im.py
eqsig/loader.py
eqsig/multiple.py
eqsig/sdof.py
eqsig/single.py
eqsig/stockwell.py
eqsig/surface.py
eqsig.egg-info/PKG-INFO
eqsig.egg-info/SOURCES.txt
eqsig.egg-info/dependency_links.txt
eqsig.egg-info/not-zip-safe
eqsig.egg-info/requires.txt
eqsig.egg-info/top_level.txt
eqsig/fns/__init__.py
eqsig/fns/average.py
eqsig/fns/frequency.py
eqsig/fns/generic.py
eqsig/fns/peaks_and_crossings.py
eqsig/fns/time_shift.py
eqsig/fns/time_step.py
examples/stockwell-example.png
tests/test_fns/__init__.py
tests/test_fns/test_average.py
tests/test_fns/test_frequency.py
tests/test_fns/test_generic.py
tests/test_fns/test_peaks_and_crossings.py
tests/test_fns/test_time_shift.py