Metadata-Version: 2.1
Name: eqsig
Version: 1.2.11
Summary: Signal processing for field and experimental data for earthquake engineering
Home-page: UNKNOWN
Author: Maxim Millen
Author-email: mmi46@uclive.ac.nz
License: MIT
Platform: UNKNOWN
Classifier: Development Status :: 5 - Production/Stable
Classifier: Intended Audience :: Science/Research
Classifier: Topic :: Scientific/Engineering
Classifier: License :: OSI Approved :: MIT License
Classifier: Programming Language :: Python :: 3
Requires-Python: >=3
Provides-Extra: test
License-File: LICENSE
